{
  "url": "https://www.who.int/news-room/fact-sheets/detail/tuberculosis",
  "title": "Tuberculosis",
  "sections": [
    {
      "heading": "Introduction",
      "content": "- Global\n- RegionsWHO Regional websitesAfricaAmericasSouth-East AsiaEuropeEastern MediterraneanWestern Pacific\n- Africa\n- Americas\n- South-East Asia\n- Europe\n- Eastern Mediterranean\n- Western Pacific\n- Home\n- Health Topics\n- All topics\n- A\n- B\n- C\n- D\n- E\n- F\n- G\n- H\n- I\n- J\n- K\n- L\n- M\n- N\n- O\n- P\n- Q\n- R\n- S\n- T\n- U\n- V\n- W\n- X\n- Y\n- Z\n- ResourcesFact sheetsFacts in picturesMultimediaPodcastsPublicationsQuestions and answersTools and toolkits\n- Fact sheets\n- Facts in pictures\n- Multimedia\n- Podcasts\n- Publications\n- Questions and answers\n- Tools and toolkits\n- PopularDengueEndometriosisExcessive heatHerpesMental disordersMpox\n- Dengue\n- Endometriosis\n- Excessive heat\n- Herpes\n- Mental disorders\n- Mpox\n- Countries\n- All countries\n- A\n- B\n- C\n- D\n- E\n- F\n- G\n- H\n- I\n- J\n- K\n- L\n- M\n- N\n- O\n- P\n- Q\n- R\n- S\n- T\n- U\n- V\n- W\n- X\n- Y\n- Z\n- RegionsAfricaAmericasEuropeEastern MediterraneanSouth-East AsiaWestern Pacific\n- Africa\n- Americas\n- Europe\n- Eastern Mediterranean\n- South-East Asia\n- Western Pacific\n- WHO in countriesData by countryCountry presenceCountry cooperation strategiesCountry office profilesStrengthening country offices\n- Data by country\n- Country presence\n- Country cooperation strategies\n- Country office profiles\n- Strengthening country offices\n- Newsroom\n- NewsroomNews releasesStatementsCampaignsEventsFeature storiesSpeechesCommentariesPhoto library\n- News releases\n- Statements\n- Campaigns\n- Events\n- Feature stories\n- Speeches\n- Commentaries\n- Photo library\n- Headlines\n- Emergencies\n- Focus onCholeraCoronavirus disease (COVID-19)Greater Horn of AfricaIsrael and occupied Palestinian territoryMpoxSudanUkraine\n- Cholera\n- Coronavirus disease (COVID-19)\n- Greater Horn of Africa\n- Israel and occupied Palestinian territory\n- Mpox\n- Sudan\n- Ukraine\n- LatestDisease Outbreak NewsSituation reportsRapid risk assessmentsWeekly Epidemiological Record\n- Disease Outbreak News\n- Situation reports\n- Rapid risk assessments\n- Weekly Epidemiological Record\n- WHO in emergenciesSurveillanceAlert and responseOperationsResearchFundingPartnersHealth emergency appealsInternational Health RegulationsIndependent Oversight and Advisory Committee\n- Surveillance\n- Alert and response\n- Operations\n- Research\n- Funding\n- Partners\n- Health emergency appeals\n- International Health Regulations\n- Independent Oversight and Advisory Committee\n- Data\n- Data at WHOData hubGlobal Health EstimatesHealth inequalityGlobal Health Obsevatory\n- Data hub\n- Global Health Estimates\n- Health inequality\n- Global Health Obsevatory\n- DashboardsTriple Billion ProgressHealth Inequality MonitorDelivery for impactCOVID-19 dashboard\n- Triple Billion Progress\n- Health Inequality Monitor\n- Delivery for impact\n- COVID-19 dashboard\n- Data collectionClassificationsSCORESurveysCivil registration and vital statisticsRoutine health information systemsHarmonized health facility assessmentGIS centre for health\n- Classifications\n- SCORE\n- Surveys\n- Civil registration and vital statistics\n- Routine health information systems\n- Harmonized health facility assessment\n- GIS centre for health\n- ReportsWorld Health StatisticsUHC global monitoring report\n- World Health Statistics\n- UHC global monitoring report\n- About WHO\n- About WHOPartnershipsCommittees and advisory groupsCollaborating centresTechnical teamsOrganizational structureWho we are\n- Partnerships\n- Committees and advisory groups\n- Collaborating centres\n- Technical teams\n- Organizational structure\n- Who we are\n- Our workActivitiesInitiativesGeneral Programme of WorkWHO Academy\n- Activities\n- Initiatives\n- General Programme of Work\n- WHO Academy\n- FundingInvestment in WHOWHO Foundation\n- Investment in WHO\n- WHO Foundation\n- AccountabilityExternal auditFinancial statementsInternal audit and investigationsProgramme BudgetResults reports\n- External audit\n- Financial statements\n- Internal audit and investigations\n- Programme Budget\n- Results reports\n- GovernanceGoverning bodiesWorld Health AssemblyExecutive BoardMember States Portal\n- Governing bodies\n- World Health Assembly\n- Executive Board\n- Member States Portal\n- Home/\n- Newsroom/\n- Fact sheets/\n- Detail/\n- Tuberculosis\n"
    },
    {
      "heading": "Key facts",
      "content": "- A total of 1.23 million people died from tuberculosis (TB) in 2024 (including 150 000 among people with HIV). Globally, TB is the world’s leading cause of death from a single infectious agent and among the top 10 causes of death.\n- TB was also both the leading killer of people with HIV in 2024 and a major cause of deaths related to antimicrobial resistance.\n- In 2024, an estimated 10.7 million people fell ill with TB worldwide, including 5.8 million men, 3.7 million women and 1.2 million children. TB is present in all countries and age groups.\n- Multidrug-resistant TB (MDR-TB) remains a public health crisis and a health security threat. Only about 2 in 5 people with drug-resistant TB accessed treatment in 2024.\n- Global efforts to combat TB have saved an estimated 83 million lives since the year 2000.\n- TB is preventable and curable.\n"
    },
    {
      "heading": "Overview",
      "content": "Tuberculosis (TB) is an infectious disease caused by bacteria that most often affects the lungs. It spreads through the air when people with TB cough, sneeze or spit.\nTuberculosis is preventable and curable.\nAbout a quarter of the global population is estimated to have been infected with TB bacteria. In general, people with TB infection don’t feel sick and are not contagious. About 5–10% of people infected with TB will eventually get symptoms and develop TB disease. Babies and children are at higher risk of developing the disease if they are infected.\nTB disease is usually treated with antibiotics and can be fatal without treatment.\nIn certain countries, the Bacille Calmette-Guérin (BCG) vaccine is given to babies or small children to prevent TB. The vaccine prevents deaths from TB and protects children from serious forms of TB.\nCertain conditions can increase a person’s risk for TB disease:\n- diabetes (high blood sugar);\n- weakened immune system (for example, from HIV);\n- undernutrition;\n- tobacco use; and\n- harmful use of alcohol.\n"
    },
    {
      "heading": "Symptoms",
      "content": "In general, people with TB infection don’t feel sick and are not contagious. Only a small proportion of people who get infected with TB will get TB disease and develop symptoms. Babies and children are at higher risk of developing the disease if they are infected.\nTB disease occurs when bacteria multiply in the body and affect different organs. TB symptoms may be mild for many months, so it is easy to spread TB to others without knowing it. Symptoms depend on which part of the body is affected. While TB usually affects the lungs, it can also affect the kidneys, brain, and spine.\nSome people with TB disease do not have any symptoms but can still spread TB.\nCommon symptoms of TB are:\n- prolonged cough (sometimes with blood);\n- chest pain;\n- weakness;\n- fatigue;\n- weight loss;\n- fever; and\n- night sweats\nThe symptoms people get depend on which part of the body is affected by TB. While TB usually affects the lungs, it can also involve the kidneys, brain, spine and skin.\n"
    },
    {
      "heading": "Prevention",
      "content": "Follow these steps to help prevent tuberculosis infection and spread:\n- Seek medical attention if you have symptoms like prolonged cough, fever and unexplained weight loss as early treatment for TB can help stop the spread of disease and improve your chances of recovery.\n- Get screened for TB if you are at increased risk, such as if you have HIV or are in contact with people who have TB in your household or workplace.\n- TB preventive treatment (or TPT) prevents infection from becoming disease. If prescribed TPT, complete the full course.\n- If you have TB, practice good hygiene when coughing, including avoiding contact with other people and wearing a mask, covering your mouth and nose when coughing or sneezing, and disposing of sputum and used tissues properly.\n- Special measures, like respirators and well-ventilated spaces are important to reduce infection in healthcare facilities and other institutions.\n"
    },
    {
      "heading": "Diagnosis",
      "content": "WHO recommends the use of rapid diagnostic tests as the initial diagnostic tests in all persons with signs and symptoms of TB.\nRapid diagnostic tests recommended by WHO include  biomarker-based point-of-care tests and molecular assays. All these tests are accurate and can provide initial results to guide treatment decisions within 48 hours of sample collection. Use of these tests will lead to major improvements in the early detection of TB and drug-resistant TB.\nDiagnosing drug-resistant forms of TB, including multidrug-resistant TB, as well as HIV-associated TB and pediatric TB can be complex. WHO recommends specific sample types, tests and strategies to detect these forms of TB to increase the chances of detecting disease early and accurately.\nA tuberculin skin test (TST), interferon gamma release assay (IGRA) or newer antigen-based skin test (TBST) can be used to identify people with TB infection. The results from these TB infection tests are used to identify which individuals with a high risk of TB will benefit most from TB preventive treatment.\n"
    },
    {
      "heading": "Treatment",
      "content": "Tuberculosis disease is treated with special antibiotics. Treatment is recommended for both TB infection and disease.\nThe most common antibiotics used are:\n- rifampicin;\n- isoniazid;\n- pyrazinamide; and\n- ethambutol.\nTo be effective, medications need to be taken daily for 4–6 months. It is dangerous to stop the medications early or without medical advice as it can prompt TB bacteria in the body to become resistant to the antibiotics.\nTB that doesn’t respond to standard drugs is called drug-resistant TB and requires treatment with different medicines.\n"
    },
    {
      "heading": "Multidrug-resistant TB (MDR-TB)",
      "content": "Drug resistance emerges when TB medicines are used inappropriately, through incorrect prescription by health care providers, poor quality drugs, or patients stopping treatment prematurely.\nMDR-TB is a form of TB caused by bacteria that do not respond to rifampicin and isoniazid, the two most effective first-line TB drugs. MDR-TB is treatable and curable by using other drugs, which tend to be more expensive and with more side effects. People exposed to MDR-TB may receive TB preventive treatment with levofloxacin.\nIn some cases, extensively drug-resistant TB or XDR-TB can develop. TB caused by bacteria that do not respond to the most effective drugs in MDR-TB treatment regimens can leave patients with very limited treatment options.\nMDR-TB remains a public health crisis. Only about 2 in 5 people with multidrug-resistant TB accessed treatment in 2024.\nIn accordance with WHO guidelines, detection of MDR-TB requires bacteriological confirmation of TB and testing for drug resistance using rapid molecular tests or culture methods.\nIn 2022, new WHO guidelines prioritized a short 6-month all-oral regimen known as BPaLM/BPaL as a treatment of choice for eligible patients. Globally in 2024, approximately 34 000 people with MDR/RR-TB were reported to have started treatment on the 6-month shorter regimens (known as BPaLM and BDLLfxC), a substantial increase from 5653 in 2023 and 1744 in 2022. The shorter duration, lower pill burden and high efficacy of this novel regimen can help ease the burden on health systems and save precious resources to further expand the diagnostic and treatment coverage for all individuals in need. WHO recommends expanded access to all-oral regimens.\n"
    },
    {
      "heading": "TB and HIV",
      "content": "People living with HIV are 12 times more likely to fall ill with TB disease than people without HIV. TB is the leading cause of death among people with HIV.\nHIV and TB form a lethal combination, each accelerating the other's progress. In 2024, about 150 000 people died of HIV-associated TB. The percentage of people who fell ill with TB and had a documented HIV test result was 82% in 2024. This was a slight increase from 81% in 2023. The WHO African Region has the highest burden of HIV-associated TB. Globally in 2024, only 61% of the estimated number of people  living with HIV who developed TB received antiretroviral therapy (ART).\nWHO first recommended collaborative TB/HIV activities to reduce morbidity and mortality from HIV-associated TB in 2004. These activities include  bidirectional screening, prevention and treatment of infection and disease. Scale-up of TB treatment and ART since 2005 is estimated to have averted 9.8 million deaths.\n"
    },
    {
      "heading": "Impact",
      "content": "TB mostly affects adults in their most productive years. However, all age groups are at risk. Over 80% of cases and deaths are in low- and middle-income countries.\nTB occurs in every part of the world. In 2024, the largest number of new TB cases occurred in the WHO South-East Asia Region (34%), followed by the Western Pacific Region (27%) and the African Region (25%). Around 87% of new TB cases occurred in the 30 high TB burden countries, with two-thirds of the global total in India (25%), Indonesia (10%), the Philippines (6.8%), China (6.5%), Pakistan (6.3%), Nigeria (4.8%), the Democratic Republic of the Congo (3.9%) and Bangladesh (3.6%). The top five countries accounted for 55% of the global total.\nGlobally, about 50% of people treated for TB and their households face total costs (direct medical expenditures, non-medical expenditures and indirect costs such as income losses) that are catastrophic (>20% of total household income). This is far from the target of the WHO End TB Strategy of zero. Those with compromised immune systems, such as people living with HIV, undernutrition or diabetes, or people who use tobacco have a higher risk of falling ill. Globally in 2024, there were an estimated 0.97 million new TB cases that were attributable to undernutrition, 0.93 million to diabetes, 0.74 million to alcohol use disorders, 0.70 million to smoking and 0.57 million to HIV infection.\n"
    },
    {
      "heading": "Investments to end TB",
      "content": "US$ 22 billion are needed annually for TB prevention, diagnosis, treatment and care to achieve global targets by 2027 agreed on at the 2023 UN high level-TB meeting.\nAs in the past decade, most of the spending on TB services in 2024 (82%) was from domestic sources. In absolute terms, Brazil, China, India, the Russian Federation and South Africa accounted for US$ 3.1 billion (64%) of the total of US$ 4.8 billion provided from domestic sources in low- and middle-income countries (LMICs), international donor funding amounted to US$ 1.1 billion, having ranged from US$ 1.1 billion to US$ 1.2 billion in almost every year since 2015. Financing for TB research and innovation, at US$ 1.2 billion in 2023, also continues to fall far short of the global target of US$ 5 billion per year. Progress to date  has been constrained by the overall level of investment.\n"
    },
    {
      "heading": "WHO response",
      "content": "WHO is working closely with countries, partners and civil society to scaler up the TB response. Six core functions are being pursued by WHO to contribute to achieving the targets of the 2023 UN High-level Meeting political declaration, Sustainable Development Goals, the WHO End TB Strategy and WHO strategic priorities.\nRelated\nWHO's work on tuberculosis\n"
    },
    {
      "heading": "Video",
      "content": "Science in 5: Facing the TB crisis\n"
    },
    {
      "heading": "Publications",
      "content": "Global Tuberculosis Report\nEnd TB Strategy\n"
    },
    {
      "heading": "Data",
      "content": "Data and analysis on TB\nFacts in pictures\nMore\nDrug-resistant tuberculosis\n- Drug-resistant tuberculosis\n- RegionsAfricaAmericasEastern MediterraneanEuropeSouth-East AsiaWestern Pacific\n- Africa\n- Americas\n- Eastern Mediterranean\n- Europe\n- South-East Asia\n- Western Pacific\n- PoliciesCybersecurityEthicsInformation disclosurePermissions and licensingPreventing sexual exploitationTerms of use\n- Cybersecurity\n- Ethics\n- Information disclosure\n- Permissions and licensing\n- Preventing sexual exploitation\n- Terms of use\n- About usCareersFrequently asked questionsLibraryProcurementPublications\n- Careers\n- Frequently asked questions\n- Library\n- Procurement\n- Publications\n- Contact us\n"
    }
  ]
}